<innermodel>
	<transform id="pose_0_grapadora" tx="17.63568115" ty="730" tz="815.5783081"  rx="1.552723289" ry="-0.01116324496" rz="0.01525052264">
	</transform>
	<transform id="pose_1_grapadora" tx="12.69768524" ty="730" tz="821.3193359"  rx="1.561745405" ry="-0.006591333542" rz="-0.8123722076">
	</transform>
	<transform id="pose_2_grapadora" tx="18.42431641" ty="730" tz="819.9522095"  rx="1.54782176" ry="0.02081660368" rz="-1.565690994">
	</transform>
	<transform id="pose_3_grapadora" tx="22.54941368" ty="730" tz="823.1948853"  rx="1.577996492" ry="-0.01537052356" rz="-2.349517107">
	</transform>
	<transform id="pose_4_grapadora" tx="12.25415039" ty="730" tz="820.9177246"  rx="1.59981215" ry="-0.001741019893" rz="-3.12400651">
	</transform>
	<transform id="pose_5_grapadora" tx="28.75513649" ty="730" tz="822.0800781"  rx="1.599643111" ry="-0.03799703717" rz="2.338836193">
	</transform>
	<transform id="pose_6_grapadora" tx="22.96026611" ty="730" tz="824.059082"  rx="1.560623527" ry="-0.05830136687" rz="1.593010068">
	</transform>
	<transform id="pose_7_grapadora" tx="13.88765717" ty="730" tz="814.4846191"  rx="1.571688056" ry="-0.02385715395" rz="0.7657167315">
	</transform>
	<transform id="pose_8_grapadora" tx="-11.5597229" ty="730" tz="1290.517456"  rx="1.559847951" ry="0.0205622036" rz="-0.5002717376">
	</transform>
	<transform id="pose_9_grapadora" tx="-14.99295044" ty="730" tz="1302.450928"  rx="1.569899917" ry="0.006535364315" rz="-1.142466187">
	</transform>
	<transform id="pose_10_grapadora" tx="-19.13508606" ty="730" tz="1288.942383"  rx="1.577273607" ry="-0.00769290654" rz="-2.052002192">
	</transform>
	<transform id="pose_11_grapadora" tx="-22.57872009" ty="730" tz="1299.102295"  rx="1.61692512" ry="-0.00821104832" rz="-2.725918531">
	</transform>
	<transform id="pose_12_grapadora" tx="-4.167377472" ty="730" tz="1288.168701"  rx="1.582792878" ry="-0.01274171658" rz="2.657312393">
	</transform>
	<transform id="pose_13_grapadora" tx="-11.45031738" ty="730" tz="1279.291382"  rx="1.598917961" ry="-0.04966503754" rz="2.074877977">
	</transform>
	<transform id="pose_14_grapadora" tx="-26.82681274" ty="730" tz="1277.20459"  rx="1.573886275" ry="-0.05122350901" rz="1.0873487">
	</transform>
	<transform id="pose_15_grapadora" tx="-25.41456604" ty="730" tz="1287.821899"  rx="1.542773128" ry="-0.09071591496" rz="0.4490467906">
	</transform>
</innermodel>
